cocorum/__init__.py
cocorum/accountapi.py
cocorum/basehandles.py
cocorum/chatapi.py
cocorum/jsonhandles.py
cocorum/scraping.py
cocorum/servicephp.py
cocorum/static.py
cocorum/uploadphp.py
cocorum/utils.py
cocorum-2.12.0.dist-info/METADATA
cocorum-2.12.0.dist-info/WHEEL
cocorum-2.12.0.dist-info/licenses/LICENSE.txt
cocorum-2.12.0.dist-info/RECORD
