Metadata-Version: 2.4
Name: cocorum
Version: 2.12.0
Summary: An unofficial Python wrapper for the Rumble Live Stream API v1.0 (beta)
Project-URL: Homepage, https://github.com/thelabcat/cocorum
Project-URL: Issues, https://github.com/thelabcat/cocorum/issues
Project-URL: Documentation, https://thelabcat.github.io/cocorum/
Project-URL: Rumble Live Stream API docs, https://rumblefaq.groovehq.com/help/how-to-use-rumble-s-live-stream-api
Author-email: Wilbur Jaywright <zargulthewizard@outlook.com>
License-File: LICENSE.txt
Keywords: api,livestream,rumble,wrapper
Classifier: Development Status :: 4 - Beta
Classifier: License :: OSI Approved :: GNU Lesser General Public License v3 or later (LGPLv3+)
Classifier: Operating System :: OS Independent
Classifier: Programming Language :: Python :: 3
Requires-Python: >=3.12
Requires-Dist: beautifulsoup4
Requires-Dist: json-five
Requires-Dist: requests
Requires-Dist: sseclient-py
